cvminigames/__init__.py
cvminigames/outp.py
cvminigames-0.0.20.dist-info/METADATA
cvminigames-0.0.20.dist-info/WHEEL
cvminigames-0.0.20.dist-info/entry_points.txt
cvminigames-0.0.20.dist-info/top_level.txt
cvminigames-0.0.20.dist-info/zip-safe
cvminigames-0.0.20.dist-info/RECORD
