Metadata-Version: 2.1
Name: cvminigames
Version: 0.0.20
Summary: cvminigames package description
Home-page: https://godatadriven.com/blog/a-practical-guide-to-setuptools-and-pyproject-toml
Author: You
Author-email: your@email.address
License: BSD 3-Clause License
Keywords: cvminigames,setuptools
Classifier: License :: OSI Approved :: BSD License
Classifier: Programming Language :: Python :: 3
Requires-Dist: marko (==1.2.1)
Requires-Dist: typer
